payment_info_api/__init__.py
payment_info_api/app/__init__.py
payment_info_api/app/api.py
payment_info_api/app/config.py
payment_info_api/app/main.py
payment_info_api/app/schemas/__init__.py
payment_info_api/app/schemas/health.py
payment_info_api/app/schemas/predict.py
payment_info_api/app/tests/__init__.py
payment_info_api/app/tests/conftest.py
payment_info_api/app/tests/test_api.py
scoringmodel/VERSION
scoringmodel/__init__.py
scoringmodel/config.yml
scoringmodel/pipeline.py
scoringmodel/predict.py
scoringmodel/train_pipeline.py
scoringmodel/config/__init__.py
scoringmodel/config/core.py
scoringmodel/data/default_of_credit_card_clients.xls
scoringmodel/data/sample_input_data.csv
scoringmodel/processing/__init__.py
scoringmodel/processing/data_manager.py
scoringmodel/processing/validation.py
scoringmodel/trainedmodel/__init__.py
scoringmodel/trainedmodel/lgbc_output_v0.0.4.pkl
test/__init__.py
test/conftest.py
test/test_predict.py
dccc_scoring_model-0.0.4.dist-info/METADATA
dccc_scoring_model-0.0.4.dist-info/WHEEL
dccc_scoring_model-0.0.4.dist-info/top_level.txt
dccc_scoring_model-0.0.4.dist-info/RECORD
